ShiXunCrypto/DualAES.py
ShiXunCrypto/SISsignature.py
ShiXunCrypto/__init__.py
ShiXunCrypto/tools.py
ShiXunCrypto-1.0.2.dist-info/LICENSE.txt
ShiXunCrypto-1.0.2.dist-info/METADATA
ShiXunCrypto-1.0.2.dist-info/WHEEL
ShiXunCrypto-1.0.2.dist-info/top_level.txt
ShiXunCrypto-1.0.2.dist-info/RECORD
